{
  "subtitle": "", 
  "description": "UMUBIRI WAWE URIMO URAHINDUKA", 
  "language": "kin_RW", 
  "title": "ESE UBWANGAVU NI IKI? ", 
  "primary_category": "718c7aadf01a4256bfc57c095d5ed255", 
  "created_at": "2015-02-20T16:21:15.543321+00:00", 
  "featured_in_category": false, 
  "modified_at": "2015-02-20T16:21:15.543523+00:00", 
  "_version": {
    "package_version": "0.3.7", 
    "language_version": "2.7.6", 
    "language_version_string": "2.7.6 (default, Mar 22 2014, 23:03:41) \n[GCC 4.8.2]", 
    "language": "python", 
    "package": "elastic-git"
  }, 
  "linked_pages": [], 
  "id": null, 
  "content": "**ESE UBWANGAVU NI IKI?  UMUBIRI WAWE URIMO URAHINDUKA**\r\n\r\n - Uzabona amabere yawe atangiye kuba manini ndetse utangire no kumera insya. Muri icyo gihe ushobora no gutangira kujya mu mihango. \r\n - Birasanzwe ko wumva umeze ukuntu utazi kandi ugakomeza gutekereza ku kuntu umubiri wawe wahindutse. Ushobora kumva warakaye, ukarakara ubusa cyangwa ukumva wihebye. Iyo wumvise muri wowe umeze gutyo, ibyiza ni uko washaka uwo muganira.\r\n - Ubwangavu cyangwa ubugimbi buba ku bakobwa n\u2019abahungu, ariko ntibibera ku myaka imwe. Uburyo ukura bushobora gutandukana n\u2019uburyo inshuti zawe zikura. Bishobora gutuma wumva uhangayitse cyangwa warasigaye inyuma \u2013 ariko wibuke ko buri wese atandukanye n'undi kandi umubiri wawe ugenda ukura mu buryo butandukanye n'ubw'abandi. \r\n\r\n**Mu bwangavu ushobora gushaka kuvugana n'inshuti zawe kurusha uko wavugana n'abantu bakuru. Ujye wibuka guhitamo inshuti nziza zishobora kugufasha gutera imbere kandi zifite intego nk'izawe.**", 
  "source": "4b9e54f1c2c547ba92fac4ee0da7ff1d", 
  "featured": false, 
  "author_tags": [], 
  "image": null, 
  "published": null, 
  "position": 0, 
  "image_host": "http://thumbor.unicore.io", 
  "slug": "what-puberty", 
  "uuid": "23c42b9c483440a29a020f6733de3f8e"
}